spo/__init__.py
spo/__version__.py
spo/api.py
spo-0.0.1.dist-info/LICENSE
spo-0.0.1.dist-info/METADATA
spo-0.0.1.dist-info/WHEEL
spo-0.0.1.dist-info/entry_points.txt
spo-0.0.1.dist-info/top_level.txt
spo-0.0.1.dist-info/RECORD
